kamy/__init__.py
kamy/commands.py
kamy-0.1.7.dist-info/entry_points.txt
kamy-0.1.7.dist-info/WHEEL
kamy-0.1.7.dist-info/METADATA
kamy-0.1.7.dist-info/RECORD
