Metadata-Version: 1.2
Name: kamy
Version: 0.1.7
Summary: This is my first package
Home-page: http://kamy.me/
License: UNKNOWN
Author: Kamyar Ghasemlou
Author-email: kamyar@kamy.me
Classifier: License :: OSI Approved :: MIT License
Classifier: Programming Language :: Python :: 3
